owlet/__init__.py
owlet-0.8.3.dist-info/LICENSE
owlet-0.8.3.dist-info/METADATA
owlet-0.8.3.dist-info/WHEEL
owlet-0.8.3.dist-info/top_level.txt
owlet-0.8.3.dist-info/RECORD
