Metadata-Version: 2.1
Name: owlet
Version: 0.8.3
Summary: A Geospatial Python Package for Field Researchers
Home-page: https://github.com/HFM3/owlet
Author: HFM3
License: UNKNOWN
Platform: UNKNOWN
Classifier: Development Status :: 4 - Beta
Classifier: Intended Audience :: Science/Research
Classifier: Topic :: Scientific/Engineering :: GIS
Classifier: Programming Language :: Python :: 3.8
Classifier: Operating System :: OS Independent
Classifier: License :: OSI Approved :: GNU General Public License v3 (GPLv3)
Classifier: Natural Language :: English
Requires-Python: >=3.8
Requires-Dist: strix (>=0.7.3)
